{"chunk_definitions":[{"row":8,"row_count":1,"visible":true,"expansion_state":0,"options":{"engine":"r","label":"setup","include":false,"dev":"png"},"document_id":"4FBC49C3","chunk_id":"csetup_chunk","chunk_label":"setup"},{"row":65,"row_count":1,"visible":true,"expansion_state":0,"options":{"engine":"r","include":false,"label":"unnamed-chunk-13","dev":"png"},"document_id":"4FBC49C3","chunk_id":"cgnrwbh0eavzl","chunk_label":"unnamed-chunk-1"},{"row":87,"row_count":1,"visible":true,"expansion_state":0,"options":{"engine":"r","label":"unnamed-chunk-14","dev":"png"},"document_id":"4FBC49C3","chunk_id":"cv4io17vcbn68","chunk_label":"unnamed-chunk-2"},{"row":153,"row_count":1,"visible":true,"expansion_state":0,"options":{"engine":"r","label":"unnamed-chunk-20","dev":"png"},"document_id":"4FBC49C3","chunk_id":"c6f46ri2h0jwn","chunk_label":"unnamed-chunk-4"},{"row":215,"row_count":1,"visible":true,"expansion_state":0,"options":{"engine":"r","label":"unnamed-chunk-21","dev":"png"},"document_id":"4FBC49C3","chunk_id":"cyxuff5hn4vqv","chunk_label":"unnamed-chunk-5"}],"doc_write_time":1709216073,"working_dir":null,"default_chunk_options":{"echo":true}}